{"styles/Grid/virtual-scrolling.css":".imagepop {\n    position: absolute;\n    background-repeat: no-repeat;\n    background-image: url(\"https://ej2.syncfusion.com/vue/demos/src/grid/images/spinner.gif\");\n    background-position: center;\n    width: 16px;\n    height: 28px;\n  }\n  \n  .e-bigger .imagepop {\n    height: 36px;\n  }\n  \n  #popup {\n    position: absolute;\n    background-color: transparent;\n    display: none;\n    z-index: 100;\n  }\n  .div-button {\n    margin: 5px 0;\n  }\n  #performanceTime {\n    float: right;\n    margin-top: 3px;\n  }\n  \n  .e-bigger #performanceTime {\n    margin-top: 8px;\n  }","public/index.html":"<!DOCTYPE html>\r\n<html lang=\"en\">\r\n\r\n<head>\r\n    <meta charset=\"utf-8\">\r\n    <meta http-equiv=\"X-UA-Compatible\" content=\"IE=edge\">\r\n    <meta name=\"viewport\" content=\"width=device-width,initial-scale=1.0\">\r\n    <link rel=\"icon\" href=\"<%= BASE_URL %>favicon.ico\">\r\n    <title>\r\n        <%= htmlWebpackPlugin.options.title %>\r\n    </title>\r\n    <link href=\"https://cdn.syncfusion.com/ej2/28.1.33/{{theme}}.css\" rel=\"stylesheet\">\r\n    <link href=\"https://maxcdn.bootstrapcdn.com/bootstrap/3.3.7/css/bootstrap.min.css\" rel=\"stylesheet\" />\r\n</head>\r\n\r\n<body>\r\n    <noscript>\r\n        <strong>We're sorry but <%= htmlWebpackPlugin.options.title %> doesn't work properly without JavaScript enabled.\r\n        Please enable it to continue.</strong>\r\n    </noscript>\r\n    <div id=\"app\"></div>\r\n    <style>\r\n            .control-section\r\n            {\r\n                margin-top: 100px;\r\n            }\r\n    </style>\r\n    <!-- built files will be auto injected -->\r\n</body>\r\n\r\n</html>\r\n","src/App.vue":"<template>\n<div class=\"col-lg-12 control-section\">\n    <div>\n        <div class='div-button'>\n            <ejs-button @click='onClick' cssClass='e-info'>Load 100K Data</ejs-button>\n            <span id=\"popup\" :style=\"display\">\n                <span id=\"gif\" class=\"imagepop\"></span>\n            </span>\n            <span id=\"performanceTime\">{{timeTaken}}</span>\n        </div>\n\n        <ejs-grid ref='grid' :dataSource=\"virtualData\" :enableVirtualization='true' :enableColumnVirtualization='true' height=400 :dataBound='hide' :editSettings='editSettings' :toolbar='toolbar'>\n            <e-columns>\n              <e-column field='SNo' headerText='S.No' width='140' :isPrimaryKey='true' :validationRules='validationSno'></e-column>\n                <e-column field='FIELD1' headerText='Player Name' width='140' :validationRules='validationRules'></e-column>\n                <e-column field='FIELD2' headerText='Year' width='100'></e-column>\n                <e-column field='FIELD3' headerText='Sports' width='160' :validationRules='validationRules' editType='dropdownedit'></e-column>\n                <e-column field='FIELD4' headerText='Country' width='160' editType='dropdownedit'></e-column>\n                <e-column field='FIELD5' headerText='LGID' width='120'></e-column>\n                <e-column field='FIELD6' headerText='GP' width='120'></e-column>\n                <e-column field='FIELD7' headerText='GS' width='120'></e-column>\n                <e-column field='FIELD8' headerText='Minutes' width='120'></e-column>\n                <e-column field='FIELD9' headerText='Points' width='130'></e-column>\n                <e-column field='FIELD10' headerText='OREB' width='130'></e-column>\n                <e-column field='FIELD11' headerText='DREB' width='130'></e-column>\n                <e-column field='FIELD12' headerText='REB' width='130'></e-column>\n                <e-column field='FIELD13' headerText='Assists' width='130'></e-column>\n                <e-column field='FIELD14' headerText='Steals' width='120'></e-column>\n                <e-column field='FIELD15' headerText='Blocks' width='120'></e-column>\n                <e-column field='FIELD16' headerText='Turnovers' width='140'></e-column>\n                <e-column field='FIELD17' headerText='PF' width='100'></e-column>\n                <e-column field='FIELD18' headerText='FGA' width='150'></e-column>\n                <e-column field='FIELD19' headerText='FGM' width='120'></e-column>\n                <e-column field='FIELD20' headerText='FTA' width='150'></e-column>\n                <e-column field='FIELD21' headerText='FTM' width='120'></e-column>\n                <e-column field='FIELD22' headerText='Three Attempted' width='170'></e-column>\n                <e-column field='FIELD23' headerText='Three Made' width='140'></e-column>\n                <e-column field='FIELD24' headerText='Post GP' width='120'></e-column>\n                <e-column field='FIELD25' headerText='Post GS' width='120'></e-column>\n                <e-column field='FIELD26' headerText='Post Minutes' width='150'></e-column>\n                <e-column field='FIELD27' headerText='Post Points' width='120'></e-column>\n                <e-column field='FIELD28' headerText='Post OREB' width='150'></e-column>\n                <e-column field='FIELD29' headerText='Post DREB' width='150'></e-column>\n                <e-column field='FIELD30' headerText='Post REB' width='130' editType='numericedit' :validationRules='validationRules'></e-column>\n            </e-columns>\n        </ejs-grid>\n    </div>\n\n</div>\n</template>\n<style scoped>\n@import \"../styles/Grid/virtual-scrolling.css\";\n</style>\n\n<script lang=\"ts\">\nimport { GridComponent, ColumnsDirective, ColumnDirective, VirtualScroll, Edit, Toolbar } from \"@syncfusion/ej2-vue-grids\";\nimport { DataManager, JsonAdaptor } from '@syncfusion/ej2-data'; \nimport { ButtonComponent } from \"@syncfusion/ej2-vue-buttons\";\n\n\nfunction generateData() {\n      let datas: any = [];\n      let names: string[] = ['VINET', 'TOMSP', 'HANAR', 'VICTE', 'SUPRD', 'HANAR', 'CHOPS', 'RICSU', 'WELLI','HILAA', 'ERNSH', 'CENTC',\n        'OTTIK', 'QUEDE', 'RATTC', 'ERNSH', 'FOLKO', 'BLONP', 'WARTH', 'FRANK', 'GROSR', 'WHITC', 'WARTH', 'SPLIR', 'RATTC', 'QUICK', 'VINET',\n        'MAGAA', 'TORTU', 'MORGK', 'BERGS', 'LEHMS', 'BERGS', 'ROMEY', 'ROMEY', 'LILAS', 'LEHMS', 'QUICK', 'QUICK', 'RICAR', 'REGGC', 'BSBEV',\n        'COMMI', 'QUEDE', 'TRADH', 'TORTU', 'RATTC', 'VINET', 'LILAS', 'BLONP', 'HUNGO', 'RICAR', 'MAGAA', 'WANDK', 'SUPRD', 'GODOS', 'TORTU',\n        'OLDWO', 'ROMEY', 'LONEP', 'ANATR', 'HUNGO', 'THEBI', 'DUMON', 'WANDK', 'QUICK', 'RATTC', 'ISLAT', 'RATTC', 'LONEP', 'ISLAT', 'TORTU',\n        'WARTH', 'ISLAT', 'PERIC', 'KOENE', 'SAVEA', 'KOENE', 'BOLID', 'FOLKO', 'FURIB', 'SPLIR', 'LILAS', 'BONAP', 'MEREP', 'WARTH', 'VICTE',\n        'HUNGO', 'PRINI', 'FRANK', 'OLDWO', 'MEREP', 'BONAP', 'SIMOB', 'FRANK', 'LEHMS', 'WHITC', 'QUICK', 'RATTC', 'FAMIA'];\n      let sport: string[] = ['Cricket', 'Football', 'Tennis', 'Golf', 'Chess', 'Dodgeball', 'Racket', 'Archery', 'Climbing', 'Hunting', 'Carrom', 'Tag', 'Novuss',\n        'Subbuteo', 'Baseball', 'Madden NFL', 'Shuffleboard', 'Badminton', 'Hockey', 'Volleyball', 'Table Tennis', 'Golf', 'Cycling', 'Running', 'Walking', 'Wireball',\n        'Town ball', 'Tee ball', 'Stool ball', 'Stick ball'];\n      let country: string[] = ['India', 'Australia', 'Ballesteros', 'Belgium', 'Brazil', 'England', 'Ethiopia', 'Finland', 'France', 'Germany', 'Britain',\n        'Argentina', 'Jamaica', 'Kenya', 'Morocco', 'Ireland', 'Norway', 'Philippines', 'Portugal', 'Romania', 'Russia', 'Scotland', 'Scottish', 'Serbia', 'Spain',\n        'Sweden', 'Switzerland', 'Netherlands', 'UK', 'Ukraine', 'US', 'Wales', 'West Indies', 'China', 'Hong Kong', 'Italy', 'Philippines', 'Turkey', 'Botswana',\n        'Sri Lanka', 'Algeria', 'Bangladesh', 'Egypt', 'Malaysia'];\n\n      for (let i: number = 0; i < 100000; i++) {\n          datas.push({\n            SNo: i + 1,\n            FIELD1: names[Math.floor(Math.random() * names.length)],\n            FIELD2: 1967 + i % 10,\n            FIELD3: sport[Math.floor(Math.random() * sport.length)],\n            FIELD4: country[Math.floor(Math.random() * country.length)],\n            FIELD5: Math.floor(Math.random() * 2000),\n            FIELD6: Math.floor(Math.random() * 1000),\n            FIELD7: Math.floor(Math.random() * 100),\n            FIELD8: Math.floor(Math.random() * 10),\n            FIELD9: Math.floor(Math.random() * 10),\n            FIELD10: Math.floor(Math.random() * 100),\n            FIELD11: Math.floor(Math.random() * 100),\n            FIELD12: Math.floor(Math.random() * 1000),\n            FIELD13: Math.floor(Math.random() * 10),\n            FIELD14: Math.floor(Math.random() * 10),\n            FIELD15: Math.floor(Math.random() * 1000),\n            FIELD16: Math.floor(Math.random() * 200),\n            FIELD17: Math.floor(Math.random() * 300),\n            FIELD18: Math.floor(Math.random() * 400),\n            FIELD19: Math.floor(Math.random() * 500),\n            FIELD20: Math.floor(Math.random() * 700),\n            FIELD21: Math.floor(Math.random() * 800),\n            FIELD22: Math.floor(Math.random() * 1000),\n            FIELD23: Math.floor(Math.random() * 2000),\n            FIELD24: Math.floor(Math.random() * 150),\n            FIELD25: Math.floor(Math.random() * 1000),\n            FIELD26: Math.floor(Math.random() * 100),\n            FIELD27: Math.floor(Math.random() * 400),\n            FIELD28: Math.floor(Math.random() * 600),\n            FIELD29: Math.floor(Math.random() * 500),\n            FIELD30: Math.floor(Math.random() * 300)\n          });\n        }\n      return datas;\n    }\n\nexport default {\n  components: {\n    'ejs-grid': GridComponent,\n    'e-columns': ColumnsDirective,\n    'e-column': ColumnDirective,\n    'ejs-button': ButtonComponent\n  },\n  data: function() {\n    return {\n        flag: true, date1: 0, date2: 0, virtualData: [], timeTaken: 'Time Taken: 0 ms',\n        display: {'display': 'none'},\n        editSettings: { allowEditing: true, allowDeleting: true },\n        toolbar: ['Add', 'Edit', 'Delete', 'Update', 'Cancel'],\n        validationSno: { required: true, digits: true },\n        validationRules: { required: true }\n    };\n  },\n  methods: {\n    show: function() {\n        (this as any).display = {'display': 'inline-block'};\n    },\n    hide: function() {\n      if ((this as any).flag && (this as any).date1) {\n        (this as any).date2 = new Date().getTime();\n        (this as any).timeTaken = \"Time Taken: \" + ((this as any).date2 - (this as any).date1) + \"ms\";\n        ((this as any).$refs.grid).ej2Instances.editSettings.allowAdding= true;\n        (this as any).flag = false;\n      }\n      (this as any).display = {'display': 'none'};\n    },\n    onClick: function (args: any) {\n      if (!(this as any).virtualData.length) {\n        (this as any).show();      \n        (this as any).virtualData = generateData();\n        (this as any).date1 = new Date().getTime();\n        (this as any).flag = true;\n      }\n    }\n  },\n  provide: {\n      grid: [VirtualScroll, Toolbar, Edit]\n  }\n};\n</script>","dependencies":"{\"vue\":\"3.3.4\",\"@syncfusion/ej2-base\":\"*\",\"@syncfusion/ej2-vue-base\":\"*\",\"@syncfusion/ej2-grids\":\"*\",\"@syncfusion/ej2-vue-grids\":\"*\",\"@syncfusion/ej2-data\":\"*\",\"@syncfusion/ej2-buttons\":\"*\",\"@syncfusion/ej2-vue-buttons\":\"*\",\"@syncfusion/ej2-vue-charts\":\"*\",\"@syncfusion/ej2-vue-maps\":\"*\",\"@syncfusion/ej2-vue-calendars\":\"*\",\"@syncfusion/ej2-vue-schedule\":\"*\",\"@syncfusion/ej2-vue-richtexteditor\":\"*\",\"@syncfusion/ej2-vue-inputs\":\"*\",\"@syncfusion/ej2-vue-navigations\":\"*\",\"@syncfusion/ej2-vue-documenteditor\":\"*\",\"@syncfusion/ej2-vue-splitbuttons\":\"*\",\"@syncfusion/ej2-vue-dropdowns\":\"*\"}","src/main.js":"import { createApp } from 'vue'\nimport App from './App.vue'\ncreateApp(App).mount('#app')"}